scpt/__init__.py
scpt/py.typed
scpt-0.0.1.dist-info/LICENSE
scpt-0.0.1.dist-info/METADATA
scpt-0.0.1.dist-info/WHEEL
scpt-0.0.1.dist-info/top_level.txt
scpt-0.0.1.dist-info/RECORD
