Metadata-Version: 2.1
Name: scpt
Version: 0.0.1
Summary: A toolbox to help keep the verbosity down when porting Bash scripts to Python
Home-page: UNKNOWN
License: UNKNOWN
Platform: UNKNOWN
Classifier: License :: OSI Approved :: MIT License
Classifier: Programming Language :: Python :: 3 :: Only
Classifier: Typing :: Typed
Classifier: Topic :: System :: Shells
Requires-Python: >=3.6
License-File: LICENSE
